revergy/__init__.py
revergy/data.py
revergy/excel.py
revergy/utils.py
revergy-0.1.0.dist-info/METADATA
revergy-0.1.0.dist-info/WHEEL
revergy-0.1.0.dist-info/RECORD
