Metadata-Version: 2.1
Name: revergy
Version: 0.1.0
Summary: Tools for data manipulation, Excel handling and other tasks related to solar parks data acquisition.
Author: Pablo Escalante
Author-email: pescalante@revergy.es
Requires-Python: >=3.9,<4.0
Classifier: Programming Language :: Python :: 3
Classifier: Programming Language :: Python :: 3.9
Classifier: Programming Language :: Python :: 3.10
Classifier: Programming Language :: Python :: 3.11
Classifier: Programming Language :: Python :: 3.12
Requires-Dist: openpyxl (>=3.1.5,<4.0.0)
Requires-Dist: pandas (>=2.2.2,<3.0.0)
Requires-Dist: pdfplumber (==0.11.4)
Requires-Dist: scipy (==1.13.0)
Requires-Dist: xlrd (>=2.0.1,<3.0.0)
